pyoselm/__init__.py
pyoselm/elm.py
pyoselm/layer.py
pyoselm/oselm.py
pyoselm/py.typed
pyoselm-1.2.0.dist-info/LICENSE
pyoselm-1.2.0.dist-info/METADATA
pyoselm-1.2.0.dist-info/WHEEL
pyoselm-1.2.0.dist-info/RECORD
