Metadata-Version: 2.1
Name: pyoselm
Version: 1.2.0
Summary: A Python implementation of Online Sequential Extreme Machine Learning (OS-ELM) for online machine learning
Home-page: https://github.com/leferrad/pyoselm
License: Apache-2.0
Keywords: machine learning,online learning,extreme learning machine,ELM,OS-ELM,neural networks,regression,classification,scikit-learn
Author: Leandro Ferrado
Author-email: leferrad@gmail.com
Requires-Python: >=3.10,<4.0
Classifier: Development Status :: 4 - Beta
Classifier: Intended Audience :: Developers
Classifier: Intended Audience :: Science/Research
Classifier: License :: OSI Approved :: Apache Software License
Classifier: Operating System :: OS Independent
Classifier: Programming Language :: Python :: 3
Classifier: Programming Language :: Python :: 3.10
Classifier: Programming Language :: Python :: 3.11
Classifier: Programming Language :: Python :: 3.12
Classifier: Topic :: Scientific/Engineering :: Artificial Intelligence
Classifier: Topic :: Scientific/Engineering :: Information Analysis
Classifier: Topic :: Software Development :: Libraries :: Python Modules
Requires-Dist: numpy (>=2.2.6,<3.0.0)
Requires-Dist: scikit-learn (>=1.7.1,<2.0.0)
Requires-Dist: scipy (>=1.14.1,<2.0.0)
Project-URL: Documentation, http://pyoselm.readthedocs.io/
Project-URL: Repository, https://github.com/leferrad/pyoselm
